spider/__init__.py
spider/__main__.py
spider/_server.py
spider/web/__init__.py
spider/web/_http.py
spider/web/_service.py
spider/web/_static.py
spider/web/responses/__init__.py
spider/web/responses/_responses.py
Spiders-0.1.1.dist-info/METADATA
Spiders-0.1.1.dist-info/WHEEL
Spiders-0.1.1.dist-info/top_level.txt
Spiders-0.1.1.dist-info/RECORD
