Metadata-Version: 2.1
Name: Spiders
Version: 0.1.1
Summary: Asynchronous python server
Home-page: https://github.com/Sparklapse/Spiders
Author: mr-josh
Author-email: mr-josh@sparklapse.com
License: UNKNOWN
Platform: UNKNOWN
Classifier: Programming Language :: Python :: 3
Classifier: Operating System :: OS Independent
Classifier: License :: OSI Approved :: Mozilla Public License 2.0 (MPL 2.0)
Classifier: Topic :: Internet :: WWW/HTTP :: HTTP Servers
Requires-Python: >=3.9
